cxc_gis/__init__.py
cxc_gis/exceptions.py
cxc_gis/flat_geometry.py
cxc_gis/mixins.py
cxc_gis/models.py
cxc_gis-0.2.1.dist-info/DESCRIPTION.rst
cxc_gis-0.2.1.dist-info/METADATA
cxc_gis-0.2.1.dist-info/RECORD
cxc_gis-0.2.1.dist-info/WHEEL
cxc_gis-0.2.1.dist-info/metadata.json
cxc_gis-0.2.1.dist-info/top_level.txt
test/__init__.py
test/test_base.py
test/test_flat_geometry.py
test/test_line.py
test/test_location.py
test/test_point.py
test/test_polyline.py
test/test_region.py
