Metadata-Version: 2.0
Name: cxc-gis
Version: 0.2.1
Summary: Geographic information system lib
Home-page: https://github.com/XiaochenCui/cxc-gis
Author: Xiaochen Cui
Author-email: jcnlcxc.new@gmail.com
License: GPLv3
Keywords: gis
Platform: UNKNOWN
Classifier: Development Status :: 1 - Planning
Classifier: Intended Audience :: Developers
Classifier: Topic :: Software Development :: Libraries :: Python Modules
Classifier: License :: OSI Approved :: GNU General Public License v3 (GPLv3)
Classifier: Programming Language :: Python :: 3
Classifier: Programming Language :: Python :: 3.6
Classifier: Programming Language :: Python :: 3 :: Only
Requires-Dist: utm
